Classfile /private/tmp/java/javawocc/Javawocc.class
  Last modified Jul 30, 2019; size 305 bytes
  MD5 checksum 5e9fa6a241f1408dd63913fb77991ff7
  Compiled from "Javawocc.java"
public class javawocc.Javawocc
  minor version: 0
  major version: 56
  flags: (0x0021) ACC_PUBLIC, ACC_SUPER
  this_class: #2                          // javawocc/Javawocc
  super_class: #3                         // java/lang/Object
  interfaces: 0, fields: 0, methods: 2, attributes: 1
Constant pool:
   #1 = Methodref          #3.#13         // java/lang/Object."<init>":()V
   #2 = Class              #14            // javawocc/Javawocc
   #3 = Class              #15            // java/lang/Object
   #4 = Utf8               <init>
   #5 = Utf8               ()V
   #6 = Utf8               Code
   #7 = Utf8               LineNumberTable
   #8 = Utf8               process
   #9 = Utf8               (I)I
  #10 = Utf8               StackMapTable
  #11 = Utf8               SourceFile
  #12 = Utf8               Javawocc.java
  #13 = NameAndType        #4:#5          // "<init>":()V
  #14 = Utf8               javawocc/Javawocc
  #15 = Utf8               java/lang/Object
{
  public javawocc.Javawocc();
    descriptor: ()V
    flags: (0x0001) ACC_PUBLIC
    Code:
      stack=1, locals=1, args_size=1
         0: aload_0
         1: invokespecial #1                  // Method java/lang/Object."<init>":()V
         4: return
      LineNumberTable:
        line 2: 0

  public static int process(int);
    descriptor: (I)I
    flags: (0x0009) ACC_PUBLIC, ACC_STATIC
    Code:
      stack=2, locals=2, args_size=1
         0: iconst_3
         1: istore_1
         2: iload_1
         3: iconst_3
         4: if_icmpne     9
         7: iconst_1
         8: ireturn
         9: iconst_2
        10: ireturn
      LineNumberTable:
        line 4: 0
        line 5: 2
        line 6: 7
        line 8: 9
      StackMapTable: number_of_entries = 1
        frame_type = 252 /* append */
          offset_delta = 9
          locals = [ int ]
}
SourceFile: "Javawocc.java"
